AUTHORS.md
ChangeLog.md
LICENSE.md
MANIFEST.in
README.md
requirements.txt
setup.py
pycamv/__init__.py
pycamv/__main__.py
pycamv/main.py
pycamv/multi.py
pycamv/proteowizard.py
pycamv/regexes.py
pycamv/utils.py
pycamv/version.py
pycamv/camv_mat/__init__.py
pycamv/export/__init__.py
pycamv/export/export.py
pycamv/export/migrations.py
pycamv/export/sql.py
pycamv/fragment/__init__.py
pycamv/fragment/compare.py
pycamv/fragment/fragments.py
pycamv/fragment/gen_sequences.py
pycamv/fragment/losses.py
pycamv/fragment/masses.py
pycamv/fragment/ms_labels.py
pycamv/fragment/validate.py
pycamv/scan/__init__.py
pycamv/scan/scan_list.py
pycamv/scan/scans.py
pycamv/search/__init__.py
pycamv/search/discoverer.py
pycamv/search/pep_query.py
pycamv/search/search.py
pycamverter.egg-info/PKG-INFO
pycamverter.egg-info/SOURCES.txt
pycamverter.egg-info/dependency_links.txt
pycamverter.egg-info/requires.txt
pycamverter.egg-info/top_level.txt