Metadata-Version: 1.1
Name: pycamverter
Version: 0.13.6
Summary: Utility for converting searched mass spec data into a format readable by CAMV
Home-page: https://github.com/white-lab/pycamverter
Author: Nader Morshed
Author-email: morshed@mit.edu
License: BSD
Platform: UNKNOWN
Classifier: License :: OSI Approved :: BSD License
Classifier: Natural Language :: English
Classifier: Operating System :: OS Independent
Classifier: Programming Language :: Python :: 2
Classifier: Programming Language :: Python :: 2.7
Classifier: Programming Language :: Python :: 3
Classifier: Programming Language :: Python :: 3.4
Classifier: Programming Language :: Python :: 3.5
Classifier: Programming Language :: Python :: 3.6
Classifier: Topic :: Scientific/Engineering
